linkesolver/__init__.py
linkesolver/remote_mix_integer_solver.py
linkesolver-0.0.2.dist-info/LICENSE
linkesolver-0.0.2.dist-info/METADATA
linkesolver-0.0.2.dist-info/WHEEL
linkesolver-0.0.2.dist-info/top_level.txt
linkesolver-0.0.2.dist-info/RECORD
