Metadata-Version: 2.1
Name: linkesolver
Version: 0.0.2
Summary: AI Solver Test Project
Author-email: plumzhenming <plumzhenming@idata.ah.cn>
License: Copyright (c) 2018 The Python Packaging Authority
Project-URL: Homepage, https://github.com/pypa/sampleproject
Project-URL: Issues, https://github.com/pypa/sampleproject
Classifier: Programming Language :: Python :: 3
Classifier: License :: OSI Approved :: MIT License
Classifier: Operating System :: OS Independent
Requires-Python: >=3.8
License-File: LICENSE
